intake_thredds/__init__.py
intake_thredds/cat.py
intake_thredds/source.py
intake_thredds-2025.2.18.dist-info/LICENSE
intake_thredds-2025.2.18.dist-info/METADATA
intake_thredds-2025.2.18.dist-info/WHEEL
intake_thredds-2025.2.18.dist-info/entry_points.txt
intake_thredds-2025.2.18.dist-info/top_level.txt
intake_thredds-2025.2.18.dist-info/RECORD
