Metadata-Version: 2.2
Name: intake-thredds
Version: 2025.2.18
Summary: Intake interface to THREDDS data catalogs.
Home-page: https://github.com/intake/intake-thredds
Maintainer: NCAR XDev Team
Maintainer-email: xdev@ucar.edu
License: Apache 2.0
Project-URL: Documentation, https://github.com/intake/intake-thredds
Project-URL: Source, https://github.com/intake/intake-thredds
Project-URL: Tracker, https://github.com/intake/intake-thredds/issues
Keywords: intake thredds siphon catalogs
Classifier: Development Status :: 4 - Beta
Classifier: License :: OSI Approved :: Apache Software License
Classifier: Operating System :: OS Independent
Classifier: Intended Audience :: Science/Research
Classifier: Programming Language :: Python
Classifier: Programming Language :: Python :: 3
Classifier: Programming Language :: Python :: 3.10
Classifier: Programming Language :: Python :: 3.11
Classifier: Programming Language :: Python :: 3.12
Classifier: Topic :: Scientific/Engineering
Requires-Python: >=3.10
License-File: LICENSE
Requires-Dist: aiohttp>=3.7
Requires-Dist: fsspec>=0.8.5
Requires-Dist: h5netcdf>=0.8.1
Requires-Dist: intake-xarray
Requires-Dist: intake>2
Requires-Dist: pydap
Requires-Dist: siphon
Requires-Dist: tqdm
Dynamic: classifier
Dynamic: description
Dynamic: description-content-type
Dynamic: home-page
Dynamic: keywords
Dynamic: license
Dynamic: maintainer
Dynamic: maintainer-email
Dynamic: project-url
Dynamic: requires-dist
Dynamic: requires-python
Dynamic: summary
